{
    "Ar36": {
        "error": 0.0014966781287498428,
        "error_type": "SEM",
        "filter_outliers_dict": {
            "filter_outliers": true,
            "iterations": 1,
            "std_devs": 3,
            "use_iqr_filtering": false,
            "use_standard_deviation_filtering": false
        },
        "fit": "linear",
        "fn": 339,
        "include_baseline_error": false,
        "n": 340,
        "outlier_excluded": [
            103
        ],
        "reviewed": true,
        "user_excluded": [],
        "value": 1.0563967581780362
    },
    "Ar37": {
        "error": 0.016512046358610265,
        "error_type": "SEM",
        "filter_outliers_dict": {
            "filter_outliers": true,
            "iterations": 1,
            "std_devs": 3,
            "use_iqr_filtering": false,
            "use_standard_deviation_filtering": false
        },
        "fit": "linear",
        "fn": 340,
        "include_baseline_error": false,
        "n": 340,
        "outlier_excluded": [],
        "reviewed": true,
        "user_excluded": [],
        "value": 0.013196987956354513
    },
    "Ar38": {
        "error": 0.005573058152935029,
        "error_type": "SEM",
        "filter_outliers_dict": {
            "filter_outliers": true,
            "iterations": 1,
            "std_devs": 3,
            "use_iqr_filtering": false,
            "use_standard_deviation_filtering": false
        },
        "fit": "linear",
        "fn": 338,
        "include_baseline_error": false,
        "n": 340,
        "outlier_excluded": [
            258,
            298
        ],
        "reviewed": true,
        "user_excluded": [],
        "value": 0.14674814365439076
    },
    "Ar39": {
        "error": 0.013624276672112284,
        "error_type": "SEM",
        "filter_outliers_dict": {
            "filter_outliers": true,
            "iterations": 1,
            "std_devs": 3,
            "use_iqr_filtering": false,
            "use_standard_deviation_filtering": false
        },
        "fit": "parabolic",
        "fn": 340,
        "include_baseline_error": false,
        "n": 340,
        "outlier_excluded": [],
        "reviewed": true,
        "user_excluded": [],
        "value": 0.003139667450519414
    },
    "Ar40": {
        "error": 0.050215395703810534,
        "error_type": "SEM",
        "filter_outliers_dict": {
            "filter_outliers": true,
            "iterations": 1,
            "std_devs": 3,
            "use_iqr_filtering": false,
            "use_standard_deviation_filtering": false
        },
        "fit": "parabolic",
        "fn": 338,
        "include_baseline_error": false,
        "n": 340,
        "outlier_excluded": [
            185,
            148
        ],
        "reviewed": true,
        "user_excluded": [],
        "value": 316.4920528444378
    }
}