{
    "Ar36": {
        "error": 0.0027072107411395224,
        "error_type": "SEM",
        "filter_outliers_dict": {
            "filter_outliers": true,
            "iterations": 2,
            "std_devs": 2
        },
        "fit": "parabolic",
        "value": 1.0533888701470957
    },
    "Ar37": {
        "error": 0.01574207958299608,
        "error_type": "SEM",
        "filter_outliers_dict": {
            "filter_outliers": true,
            "iterations": 2,
            "std_devs": 2
        },
        "fit": "linear",
        "value": -0.008822960902011226
    },
    "Ar38": {
        "error": 0.004696502219369567,
        "error_type": "SEM",
        "filter_outliers_dict": {
            "filter_outliers": true,
            "iterations": 2,
            "std_devs": 2
        },
        "fit": "linear",
        "value": 0.1468764607096056
    },
    "Ar39": {
        "error": 0.012813158251540065,
        "error_type": "SEM",
        "filter_outliers_dict": {
            "filter_outliers": true,
            "iterations": 2,
            "std_devs": 2
        },
        "fit": "parabolic",
        "value": -0.020188714043278634
    },
    "Ar40": {
        "error": 0.045688850349315614,
        "error_type": "SEM",
        "filter_outliers_dict": {
            "filter_outliers": true,
            "iterations": 2,
            "std_devs": 2
        },
        "fit": "parabolic",
        "value": 315.12620805336894
    }
}