{
    "Ar36": {
        "error": 0.0024919080071688442,
        "error_type": "SEM",
        "filter_outliers_dict": {
            "filter_outliers": true,
            "iterations": 2,
            "std_devs": 2
        },
        "fit": "parabolic",
        "value": 1.0391416321925493
    },
    "Ar37": {
        "error": 0.013402261579423104,
        "error_type": "SEM",
        "filter_outliers_dict": {
            "filter_outliers": true,
            "iterations": 2,
            "std_devs": 2
        },
        "fit": "linear",
        "value": 0.00410824823328408
    },
    "Ar38": {
        "error": 0.004585030219566258,
        "error_type": "SEM",
        "filter_outliers_dict": {
            "filter_outliers": true,
            "iterations": 2,
            "std_devs": 2
        },
        "fit": "linear",
        "value": 0.15721721247778386
    },
    "Ar39": {
        "error": 0.013555947233645067,
        "error_type": "SEM",
        "filter_outliers_dict": {
            "filter_outliers": true,
            "iterations": 2,
            "std_devs": 2
        },
        "fit": "parabolic",
        "value": 0.004413737541628285
    },
    "Ar40": {
        "error": 0.04690782134451208,
        "error_type": "SEM",
        "filter_outliers_dict": {
            "filter_outliers": true,
            "iterations": 2,
            "std_devs": 2
        },
        "fit": "parabolic",
        "value": 313.06242225875394
    }
}